MANIFEST.in
README.md
setup.py
time_kong/__init__.py
time_kong/time_kong.py
time_kong.egg-info/PKG-INFO
time_kong.egg-info/SOURCES.txt
time_kong.egg-info/dependency_links.txt
time_kong.egg-info/top_level.txt
time_kong/test/__init__.py
time_kong/test/time_kong_test.py