Metadata-Version: 2.1
Name: time-kong
Version: 0.0.3
Summary: A useful time transform util, transforms between string, timestamp and datetime format
Home-page: https://github.com/PurpleSun/time_kong
Author: fanwei.zeng
Author-email: stayblank@gmail.com
License: MIT License
Keywords: time,transform,converter,adaptor
Platform: any
